json_to_elan/__init__.py
json_to_elan/data/.gitkeep
json_to_elan/data/audio_1.json
json_to_elan/make_elan.py
json_to_elan-0.1.17.dist-info/entry_points.txt
json_to_elan-0.1.17.dist-info/WHEEL
json_to_elan-0.1.17.dist-info/METADATA
json_to_elan-0.1.17.dist-info/RECORD
