Metadata-Version: 2.1
Name: json-to-elan
Version: 0.1.17
Summary: The script reads a JSON file (or folder) and generates an ELAN file to match.
Home-page: https://github.com/CoEDL/json-to-elan
Author: Ben Foley
Author-email: ben@cbmm.io
Requires-Python: >=3.7,<4.0
Classifier: Programming Language :: Python :: 3
Classifier: Programming Language :: Python :: 3.10
Classifier: Programming Language :: Python :: 3.7
Classifier: Programming Language :: Python :: 3.8
Classifier: Programming Language :: Python :: 3.9
Requires-Dist: pympi-ling (>=1.70.2,<2.0.0)
Project-URL: Repository, https://github.com/CoEDL/json-to-elan
